lemon/__init__.py
lemon/explainer.py
lemon/explanation.py
lemon/kernels.py
lemon_explainer-0.0.3.dist-info/METADATA
lemon_explainer-0.0.3.dist-info/WHEEL
lemon_explainer-0.0.3.dist-info/licenses/LICENSE
lemon_explainer-0.0.3.dist-info/RECORD
