Metadata-Version: 2.3
Name: lemon-explainer
Version: 0.0.3
Summary: Explaining the predictions of any machine learning model
Project-URL: Homepage, https://github.com/iamDecode/lemon
Author-email: Dennis Collaris <d.collaris@me.com>
License-Expression: BSD-2-Clause
License-File: LICENSE
Classifier: Intended Audience :: Developers
Classifier: Intended Audience :: Science/Research
Classifier: License :: OSI Approved :: BSD License
Classifier: Operating System :: OS Independent
Classifier: Programming Language :: Python :: 3
Classifier: Topic :: Scientific/Engineering
Classifier: Topic :: Software Development
Requires-Python: >=3.7
Requires-Dist: matplotlib
Requires-Dist: numpy
Requires-Dist: pandas
